owimetadatabase_preprocessor/__init__.py
owimetadatabase_preprocessor/fatigue/__init__.py
owimetadatabase_preprocessor/fatigue/data_objects.py
owimetadatabase_preprocessor/fatigue/io.py
owimetadatabase_preprocessor/geometry/__init__.py
owimetadatabase_preprocessor/geometry/io.py
owimetadatabase_preprocessor/geometry/processing.py
owimetadatabase_preprocessor/geometry/structures.py
owimetadatabase_preprocessor/io.py
owimetadatabase_preprocessor/locations/__init__.py
owimetadatabase_preprocessor/locations/io.py
owimetadatabase_preprocessor/results/__init__.py
owimetadatabase_preprocessor/results/io.py
owimetadatabase_preprocessor/soil/__init__.py
owimetadatabase_preprocessor/soil/io.py
owimetadatabase_preprocessor/soil/processing/__init__.py
owimetadatabase_preprocessor/soil/processing/soil_pp.py
owimetadatabase_preprocessor/soil/visualization/__init__.py
owimetadatabase_preprocessor/soil/visualization/soil_visualizer.py
owimetadatabase_preprocessor/utility/__init__.py
owimetadatabase_preprocessor/utility/exceptions.py
owimetadatabase_preprocessor/utility/utils.py
owimetadatabase_preprocessor-0.10.6.dist-info/WHEEL
owimetadatabase_preprocessor-0.10.6.dist-info/METADATA
owimetadatabase_preprocessor-0.10.6.dist-info/RECORD
