Metadata-Version: 2.3
Name: owimetadatabase-preprocessor
Version: 0.10.6
Summary: Package for preprocessing data from owimetadatabase.
Keywords: owimetadatabase
Author: arsmlnkv
Author-email: arsmlnkv <melnikov.arsene@gmail.com>
License:                     GNU GENERAL PUBLIC LICENSE
Classifier: License :: OSI Approved :: GNU General Public License v3 (GPLv3)
Classifier: Programming Language :: Python :: 3
Classifier: Programming Language :: Python :: 3 :: Only
Classifier: Programming Language :: Python :: 3.9
Classifier: Programming Language :: Python :: 3.10
Classifier: Programming Language :: Python :: 3.11
Classifier: Programming Language :: Python :: 3.12
Classifier: Programming Language :: Python :: 3.13
Requires-Dist: filelock==3.19.1 ; python_full_version < '3.10'
Requires-Dist: filelock>=3.20.3 ; python_full_version >= '3.10'
Requires-Dist: fonttools==4.60.2 ; python_full_version < '3.10'
Requires-Dist: fonttools>=4.61.0 ; python_full_version >= '3.10'
Requires-Dist: plotly>=5.19.0
Requires-Dist: requests>=2.32.0
Requires-Dist: matplotlib==3.9.4 ; python_full_version < '3.10'
Requires-Dist: matplotlib>=3.10.0 ; python_full_version >= '3.10'
Requires-Dist: numpy>=1.26.0,<2.0.0 ; python_full_version < '3.11'
Requires-Dist: numpy>=2.0.0 ; python_full_version >= '3.11'
Requires-Dist: pandas>=2.0.0
Requires-Dist: groundhog>=0.11.0
Requires-Dist: pyproj>=3.6.0,<3.7.0 ; python_full_version < '3.10'
Requires-Dist: pyproj>=3.7.0,<3.7.2 ; python_full_version == '3.10.*'
Requires-Dist: pyproj>=3.7.2 ; python_full_version >= '3.11'
Requires-Dist: scipy<1.14.0 ; python_full_version < '3.10'
Requires-Dist: scipy>=1.14.0,<1.16.0 ; python_full_version == '3.10.*'
Requires-Dist: scipy>=1.16.0 ; python_full_version >= '3.11'
Requires-Dist: tqdm>=4.66.0
Requires-Dist: jinja2>=3.1.6
Requires-Dist: urllib3>=2.6.3
Requires-Dist: virtualenv>=20.36.1
Requires-Python: >=3.9, <3.14
Project-URL: homepage, https://owi-lab.github.io/owimetadatabase-preprocessor/
Project-URL: repository, https://github.com/OWI-Lab/owimetadatabase-preprocessor
Project-URL: documentation, https://owi-lab.github.io/owimetadatabase-preprocessor/
